env/__init__.py
env/driver_cp210x/.DS_Store
env/driver_cp210x/CP210x_Universal_Windows_Driver/CP210xVCPInstaller_x64.exe
env/driver_cp210x/CP210x_Universal_Windows_Driver/CP210xVCPInstaller_x86.exe
env/driver_cp210x/CP210x_Universal_Windows_Driver/CP210x_Universal_Windows_Driver_ReleaseNotes.txt
env/driver_cp210x/CP210x_Universal_Windows_Driver/SLAB_License_Agreement_VCP_Windows.txt
env/driver_cp210x/CP210x_Universal_Windows_Driver/dpinst.xml
env/driver_cp210x/CP210x_Universal_Windows_Driver/silabser.cat
env/driver_cp210x/CP210x_Universal_Windows_Driver/silabser.inf
env/driver_cp210x/CP210x_Universal_Windows_Driver/arm/silabser.sys
env/driver_cp210x/CP210x_Universal_Windows_Driver/arm64/silabser.sys
env/driver_cp210x/CP210x_Universal_Windows_Driver/x64/silabser.sys
env/driver_cp210x/CP210x_Universal_Windows_Driver/x86/silabser.sys
env/driver_cp210x/macOS_VCP_Driver/SiLabsUSBDriverDisk.dmg
env/driver_cp210x/macOS_VCP_Driver/macOS_VCP_Driver_Release_Notes.txt
media/__init__.py
media/dnd.png
media/logo.png
media/logo_mini.png
media/usb_port_icon.png
media/wifi_icon.png
micrOS/__init__.py
micrOS/micropython/esp32-20251209-v1.27.0.bin
micrOS/micropython/esp32c3-20251209-v1.27.0.bin
micrOS/micropython/esp32c6-20251209-v1.27.0.bin
micrOS/micropython/esp32cam-v1.21.0_camera.bin
micrOS/micropython/esp32s2-20251209-v1.27.0.bin
micrOS/micropython/esp32s2-LOLIN_MINI-20251209-v1.27.0.bin
micrOS/micropython/esp32s3-4MBflash-20241129-v1.24.1.bin
micrOS/micropython/esp32s3-8MBflash-20251209-v1.27.0.bin
micrOS/micropython/esp32s3_spiram_oct-20251209-v1.27.0.bin
micrOS/micropython/rpi-pico-w-20251209-v1.27.0.uf2
micrOS/micropython/tinypico-20251209-v1.27.0.bin
micrOS/release_info/micrOS_ReleaseInfo/system_analysis_sum.json
micrOS/source/.DS_Store
micrOS/source/Auth.py
micrOS/source/Common.py
micrOS/source/Config.py
micrOS/source/Debug.py
micrOS/source/Espnow.py
micrOS/source/Files.py
micrOS/source/Hooks.py
micrOS/source/InterConnect.py
micrOS/source/Interrupts.py
microsdevtoolkit-2.26.2.dist-info/licenses/LICENSE
microsdevtoolkit-2.26.2.dist-info/METADATA
microsdevtoolkit-2.26.2.dist-info/WHEEL
microsdevtoolkit-2.26.2.dist-info/top_level.txt
microsdevtoolkit-2.26.2.dist-info/RECORD
