Metadata-Version: 2.4
Name: micrOSDevToolKit
Version: 2.26.2
Summary: Development and deployment environment for micrOS, the diy micropython automation OS (IoT)
Home-page: https://github.com/BxNxM/micrOS
Author: Marcell Ban
Author-email: miros.framework@gmail.com
License: MIT
Project-URL: Bug Tracker, https://github.com/BxNxM/micrOS/issues
Project-URL: GitHub Discussions, https://github.com/BxNxM/micrOS/discussions
License-File: LICENSE
Requires-Dist: adafruit-ampy
Requires-Dist: mpremote
Requires-Dist: esptool
Requires-Dist: ipaddress
Requires-Dist: netaddr
Requires-Dist: pylint
Requires-Dist: pyserial
Requires-Dist: resources
Requires-Dist: flask
Requires-Dist: flask_restful
Requires-Dist: numpy
Requires-Dist: json2html
Requires-Dist: requests
Requires-Dist: Flask-BasicAuth
Requires-Dist: soundfile
Dynamic: author
Dynamic: author-email
Dynamic: description
Dynamic: description-content-type
Dynamic: home-page
Dynamic: license
Dynamic: license-file
Dynamic: project-url
Dynamic: requires-dist
Dynamic: summary
